litefs.py
litefs-0.3.0.dist-info/LICENSE
litefs-0.3.0.dist-info/METADATA
litefs-0.3.0.dist-info/WHEEL
litefs-0.3.0.dist-info/entry_points.txt
litefs-0.3.0.dist-info/top_level.txt
litefs-0.3.0.dist-info/RECORD
